{
    "id": 3,
    "title": "Centrum Wsparcia Psychologicznego",
    "description": "Bezpłatne konsultacje psychologiczne, grupy wsparcia i warsztaty rozwoju osobistego",
    "content": "Projekt zakładał utworzenie ośrodka oferującego bezpłatne konsultacje psychologiczne, grupy wsparcia oraz warsztaty rozwoju osobistego dla osób z niepełnosprawnością. Celem jest wzmocnienie ich zdrowia psychicznego, budowanie pewności siebie oraz przeciwdziałanie izolacji społecznej. Wnioskodawca rozpoczął pracę nad ośrodkiem od stycznia 2024 r. W tym czasie Wnioskodawca wybrał lokalizację ośrodka (Żywiec woj. Śląskie), wyselekcjonował specjalistów, rozpoczął kampanię informacyjną o idei powstania ośrodka oraz jest w trakcie realizacji kampanii fundraisingowej skierowanej do darczyńców korporacyjnych.",
    "images": ["projects/3/centrum_wsparcia.jpg"],
    "date": "Zakończony",
    "allowSubscription": true
  }